{
    "weeks": [
        {
            "category_id": "24",
            "category_name": "Entertainment",
            "end_date": "11/21/2017, 00:00:00",
            "number_of_videos": 95,
            "start_date": "11/14/2017, 00:00:00",
            "total_views": 48469719,
            "video_ids": [
                "bAkEd8r7Nnw",
                "i6UcDD9KtXQ",
                "4XiCjg0E8Go",
                "hXBqZ1YKAcU",
                "gUKIhe9DJpk",
                "BlVJWZMhg7E",
                "Ax1P5Q8Kr9g",
                "imCgDwq9esc",
                "0s6-iFoCFNQ",
                "KH-NMuBWQWE",
                "q-lY3912MD8",
                "coOKvrsmQiI",
                "tr1Loa7r7sY",
                "v6ieO1vn4c8",
                "seGgZp-XYdM",
                "3gKUzizcwKk",
                "DbJ2s_g1oDc",
                "MMGrzOu1amQ",
                "j4QVVe5paHg",
                "vUe5ouo95W8",
                "FgnsA0ckebE",
                "IkWxMG-JDk4",
                "GHPh5ED7mlo",
                "pcWKpGzhgq4",
                "QqAK822pdYw",
                "IFtFzBIPBFo",
                "EmXiFUzz33c",
                "0O2IAz1E9Ts",
                "d380meD0W0M",
                "PIp5xKRsSck",
                "fpxBxp9QKrk",
                "hhtzBUFGfWM",
                "lVsogHpzi9g",
                "iE_bfDcy0iQ",
                "VD1QOLIhvzA",
                "LXDAu8DnALw",
                "MbSlZKzizxQ",
                "iozi0XkOJG8",
                "0oj_NpgyZ5Q",
                "SfFKLEOOh2A",
                "jEtTDPkjoFc",
                "p8XP7A7kvzM",
                "nVTNrp1RuEI",
                "PliRMGvytnA",
                "hbhbu_Kf424",
                "6u4S5hC1aWk",
                "w5N2XLzit-E",
                "x3-C132jLvs",
                "WrIbtWTMfVs",
                "muzbUiBIZyM",
                "8hKbIhrb1WU",
                "2c0s4Ix3ngc",
                "VwpYuT2cr9I",
                "0UJ54iT4yIU",
                "LOFCVaHrZ4Y",
                "YkfE8hHUzt4",
                "V7LeRxl59M4",
                "w1s5ElKmQm4",
                "2h6k6eg_RmM",
                "fPcnfGfE4So",
                "TCXjLPtPMec",
                "6fv7CqCjiJw",
                "UdcOGSOnEDM",
                "4VqH3Ecx2R0",
                "5nlG0svf9t4",
                "8KT1UCsOE74",
                "nRafaCcfrcI",
                "P6YLNeYZ364",
                "2jNFymV3J-M",
                "YTYXKQescCQ",
                "LUzsOyWp9lw",
                "JzCsM1vtn78",
                "NpX3DZxAjSc",
                "ctWhgovItVs",
                "ovXXvT0g6qY",
                "znKxu09P_H8",
                "WhnHKIT9124",
                "8KT1UCsOE74",
                "WSEdCMHiUlg",
                "xotnmcmktLw",
                "Rb8_EdTYjXI",
                "gT6KRNu-MBs",
                "Xu7ycyZWPiw",
                "KJkFpBScnyo",
                "jUiP543q35k",
                "HdSLKZ6LN94",
                "gkznH1SpVec",
                "l7bt05YkRFk",
                "lTshJ-2GVKM",
                "2bAixXh2fU0",
                "-3c-V5K2p88",
                "r3HjK4fur4c",
                "oGSNSLD8rcw",
                "S8kr0j1xNcg",
                "vIVaLtJmyPs"
            ]
        },
        {
            "category_id": "10",
            "category_name": "Music",
            "end_date": "11/28/2017, 00:00:00",
            "number_of_videos": 33,
            "start_date": "11/21/2017, 00:00:00",
            "total_views": 89553753,
            "video_ids": [
                "KFaMZUarksA",
                "gv_d2UoJp54",
                "w2Es7-c9GAk",
                "gJPt8ruo2BQ",
                "hzaozYJLnrI",
                "M6LTqtYKDtI",
                "UceaB4D0jpo",
                "byLufx7Izfg",
                "pOzMKakMpTU",
                "kTlv5_Bs8aw",
                "LgmxMuW6Fsc",
                "hPHffFAogVM",
                "GxkLy_mvGXE",
                "mYSxQT5c2wk",
                "-ZNmbKxeV7E",
                "UJngK9Pfj_4",
                "fqtm0Zolt78",
                "xmU0s2QtaEY",
                "W_O0sn-ockI",
                "cB9_r4HSIK8",
                "joJ-3cAjjbQ",
                "6ug9zvC9pJM",
                "RP3UsFrDJfY",
                "wlS6Ix7mA0w",
                "kfvH72JpGDY",
                "g7_uKDsv7HM",
                "EBt_88nxG4c",
                "RSRzIrOqaN4",
                "IumYMCllMsM",
                "_7rvYV_YmaQ",
                "ON5YYRxcgVM",
                "nUv22OHdjQU",
                "V3EYjVPRClU"
            ]
        },
        {
            "category_id": "24",
            "category_name": "Entertainment",
            "end_date": "12/05/2017, 00:00:00",
            "number_of_videos": 106,
            "start_date": "11/28/2017, 00:00:00",
            "total_views": 84734611,
            "video_ids": [
                "foTjlGz-u50",
                "fvEwHI4iRjs",
                "hbEQ568X8U0",
                "QGoW0QQdLZ0",
                "oyh5eRu1oBU",
                "D5wzLPRXeXk",
                "eJXcEbEUNpQ",
                "8Ab20zksSk8",
                "CV0J3Bq3BIc",
                "5lGiLmcyCDk",
                "HmhKdhF2bMI",
                "KYqXrCigcAU",
                "pjagqAGyoS0",
                "ucg-sjC59tQ",
                "xXWxHLj73YY",
                "qvkVv678Fj4",
                "1Mh71Uz8Cmk",
                "3U4nlSualNc",
                "KXHrCBkIxQQ",
                "SFr0fCgrTNQ",
                "eUyb51fxFw4",
                "yKkheNpuOKU",
                "kNx3YboB4dQ",
                "rdJdJpwmcKU",
                "Pi1WvelLak8",
                "Ys9ziXRfEMw",
                "kehML-RAkd4",
                "2HboMs0vbsE",
                "UaR3Y1dqVZk",
                "e5N_Tq1EtRQ",
                "8z_cg5CypRc",
                "CB9ZqoPdPho",
                "gJM6BlOXaPY",
                "wjoeVwJTUTA",
                "3XklsSF53pc",
                "y97FK4GrsZg",
                "_xGKlNzipdU",
                "yE0YDv0yFKQ",
                "F0YZxsrwRo8",
                "yZJXUeh-fv0",
                "NqntFonA2iY",
                "OZqsFkJpvj0",
                "k7yYOUOndsc",
                "0EQuVfP-vXs",
                "fWJrqDkZMWU",
                "535YZSfWx20",
                "RtjSIWxgqDo",
                "nI8Cti0_T00",
                "rLMx0X3SeMI",
                "0qpE8IHz3go",
                "wa9ZyarpM2U",
                "85GSILNh6U4",
                "O4OFkLx7AeI",
                "06BLwc1XSis",
                "CHp639vhUJg",
                "vhSB6Nry6MM",
                "U-jYItX_Yvg",
                "pDi7cezk9CA",
                "M6ahKUrCNNM",
                "-IgvPPniOrU",
                "ZfHiw_LFNGw",
                "ZrM_I0LwZAI",
                "nZCmUBJrxFs",
                "nPeYAsLYALA",
                "C1Qhrip9UHY",
                "aBefE9RAIz8",
                "515lLZS082U",
                "DAlj6xXR5nw",
                "NV1WmHaVhdI",
                "6ZfuNTqbHE8",
                "lob8UarRQss",
                "2azf_w6FW5g",
                "g-VRIh6dBVI",
                "NrDbRPWdx8M",
                "lIkknpTxU1U",
                "L54yDEcL2vI",
                "HFCfYCewHuA",
                "0leOMelIV3M",
                "PoabRJfEs-g",
                "iP66hpQySmg",
                "ij6-Y01JnWM",
                "Mh5AysE03-I",
                "hBvcngHRTFg",
                "TyIsOSjKBbQ",
                "3o_s7qNvt2U",
                "SH9fZcyl3ng",
                "U-v6HDIdC94",
                "BOQ-wZQhZZo",
                "Tkz_3RgvfLc",
                "YylVAe1SYXw",
                "VMsrHhGiCKs",
                "8kFnLQySIzU",
                "FzMZnDWWQZk",
                "veVBbxZyzKU",
                "NhPOM5W-SBw",
                "rm9BFh_jaRU",
                "Nb1IUSw16ok",
                "irVe0wQkMXg",
                "N8dLlRBaDtE",
                "LBDHE19PaDo",
                "mY2d4XWe0Ag",
                "NrSD3bFhCt4",
                "QmAyVRB46P8",
                "a8XSR52clAI",
                "p1f6xbi5CEQ",
                "BoGOBJBNyUI"
            ]
        },
        {
            "category_id": "24",
            "category_name": "Entertainment",
            "end_date": "12/12/2017, 00:00:00",
            "number_of_videos": 117,
            "start_date": "12/05/2017, 00:00:00",
            "total_views": 146092495,
            "video_ids": [
                "yWwPxWcsVHM",
                "KH618UYl7hg",
                "ArfmBDEwRT8",
                "O-H_Ybmtu_U",
                "VLcDEY_JMtA",
                "Xm8P0mOC8Do",
                "nACoGA3CX9o",
                "mBfaXBqq_k8",
                "gP6uGOLeG0M",
                "ZQc34LzQeZ8",
                "p1sxc3V0lzQ",
                "czhSzmxN3WU",
                "efWFb8arD_4",
                "kbx-qZnTr-0",
                "YQJ3OzoyTnE",
                "qLVZiKDNxtw",
                "JQYgOUt57I8",
                "wflQGe3Bzi0",
                "u9iZKqdXHug",
                "kTl-s4qRMqU",
                "j2vP8ordkYc",
                "jxRBzs9C3eU",
                "pjagqAGyoS0",
                "E8UtZdpXe-0",
                "qXBlB2ZD1rw",
                "00M6gHlkeko",
                "xsfT-qiJkv0",
                "v5yJnvJb17A",
                "wAOaICfJ_vU",
                "-4469zeATws",
                "7kQaNePHkiI",
                "DEM8ngzmQzo",
                "fuHcdFPBKy0",
                "YbFCADgXXK8",
                "7N3ERfi6WHM",
                "XT8bnSK29Ek",
                "J0REYqmmPAI",
                "X6iJ0hPpGec",
                "HXpNGJ2yze8",
                "QK_iX5cPDhE",
                "Q8WIJGT9Qgg",
                "dsNNfiA6qjs",
                "6H87y6cGbC0",
                "266EI7hdjFs",
                "T5jQuJfZaJU",
                "Yj8D7HU6tNA",
                "Hk5bgB77VHM",
                "UEGo_DJHkeI",
                "Y0_BwaMojpQ",
                "Y5M1i3UzkjI",
                "SMrWMRQIevw",
                "pHcJ0L7tEyw",
                "vW7H-DKivX8",
                "Gb0xyCUf7SE",
                "QWce9T6lINs",
                "ZLKgwbKRr1c",
                "Wj-hVo3aqWY",
                "1xny74rHmyY",
                "mGkwgpEQNZA",
                "mkpINSUnDpA",
                "6gnCcJ-vqt4",
                "FlsCjmMhFmw",
                "QNXHLGC1FuA",
                "qgTtyfgzGc0",
                "5wKYV-9Tq1o",
                "TekLn0qk4ig",
                "hR6agVkRRUo",
                "iAxYEkEkCqo",
                "GMftwHfXnp4",
                "5EPJqX1vmFk",
                "Kf1owfS-GM8",
                "sI7sTwCFWP4",
                "yVKw88lmoDA",
                "sQrtgYiW71o",
                "72gsrslfoF4",
                "v9ObsREADw4",
                "PiI150VpvV8",
                "TeY3ijusHns",
                "vn9mMeWcgoM",
                "7icFIMa3Qk8",
                "Gp40Uztk3bg",
                "YfT9sjc4bf4",
                "qxo9OzKb-iw",
                "5ELQ6u_5YYM",
                "s04fn1wtKg0",
                "uPimPuPEWzk",
                "dpKT3cAyG_g",
                "qOJ_2I3hhgs",
                "uUxNjBoHxBw",
                "6ZfuNTqbHE8",
                "Hj-CC-kPMeE",
                "gL_7eIrLaGQ",
                "1sl5KJ69qiA",
                "kQvRWXuMd5M",
                "_GuyKCLrJqk",
                "HFCfYCewHuA",
                "e77J4g0LMOk",
                "jSYgh4z1-dg",
                "mzqYuyaAh5Y",
                "dnEBuvfcFJE",
                "B74dKMxfaCE",
                "ex_sBZXU6iU",
                "boUhnE06eIs",
                "3pRp-ZM59H4",
                "LmxyIswRN8E",
                "oEqvJIKXAvk",
                "fHWaKx5MnNc",
                "1u8QO_r9mhw",
                "sRyJZJDjm3M",
                "E9XRNkJxEFk",
                "yB4ogLIYBsE",
                "JBDWIGpKnwM",
                "v1Nn8ZejIHw",
                "Sw_K24hbRjU",
                "p7CsTuHv5As",
                "5Xe6E8HGj24",
                "Odum0r9gxA8"
            ]
        },
        {
            "category_id": "24",
            "category_name": "Entertainment",
            "end_date": "12/19/2017, 00:00:00",
            "number_of_videos": 93,
            "start_date": "12/12/2017, 00:00:00",
            "total_views": 77696589,
            "video_ids": [
                "-H90GPnH1q8",
                "NsUQU3r2nsM",
                "hS4XXstzocY",
                "TZSVf-yD7N8",
                "UCZVSr2Xt2k",
                "oS07bQTPZ20",
                "5uXsCaakZD8",
                "7tKmcZob5BM",
                "8JBfRSeYofM",
                "QXcbVHFE2bo",
                "DevvFHFCXE8",
                "jehMXPadHS0",
                "acllEsTUYAU",
                "0oQYo2VuXgU",
                "UDdUDrSQbdY",
                "XzDqydDwmD8",
                "-K9ujx8vO_A",
                "6KMl4oliDLc",
                "E1p8EJSnwMA",
                "VcB4hgT4jIc",
                "fOhB5JyEkOQ",
                "khPLWaBioOs",
                "nMfBqC7BuTA",
                "nxM2wUaqDl8",
                "d_uCwD394A8",
                "rKFoy7dFym4",
                "lUXWRSF9aiw",
                "qhQqaLZnGoc",
                "UH0nTHb6OdY",
                "ii3n7hYQOl4",
                "VZaLxRPbE40",
                "qS-r7EsAzNg",
                "RkxRn8wiYxo",
                "0Iyjm5crBfM",
                "hu_4yAZVNsU",
                "MDOtD8gBaAo",
                "B4WBB8gAwTE",
                "D7sj7L1uLiw",
                "EtfIzNdt9Ac",
                "sbLox-Onjhg",
                "00zDrnvB1Os",
                "qTBYE8BFVxo",
                "CBn2M-3Safw",
                "9V0hw6QjzSw",
                "ZsGsHYct-vk",
                "w-bWd6Y0_5E",
                "g0_EfWp1ocY",
                "0wx849AmSm8",
                "vn9mMeWcgoM",
                "isJgzkuvcjU",
                "4vZJn6r0dRw",
                "B4WBB8gAwTE",
                "GucsPYIZLn4",
                "y88ZsdYpELk",
                "r4VJ8o6yqzM",
                "3ta8sjjnzk0",
                "V-0UCEWtLa0",
                "Def-3JldSi0",
                "3Fus-_sshmQ",
                "eWIIwTzB0_0",
                "Euskgw9Z-VQ",
                "knaCsR6dr58",
                "cSp1dM2Vj48",
                "eL9RB_jG6SY",
                "j0VZtMVAxg4",
                "mbzXQK3Q860",
                "3QeGFX5gl5I",
                "Y3bZ1iom5Dg",
                "iKjEoPA0LlY",
                "9ohJuyUydoo",
                "8oKl_qDJHt4",
                "RlNHFwRRO-Q",
                "SGtiZlq4n8k",
                "1Znl8OUBa_o",
                "8NJ7aI1ioXM",
                "5HuUnJHf6yk",
                "XkVwqEdYlNA",
                "h_67XloYXTc",
                "BCqM-6c3VNA",
                "eXx7vn4iNLI",
                "iD1looAQU7s",
                "9mwM1VB9qs0",
                "Jnei1md-Ia0",
                "yCBaFlp-Gr0",
                "oubzC5SLZiE",
                "nTAXKTAAdW0",
                "yPCFroqRFQ8",
                "qd9NIPDd-DI",
                "o4duS8xz3h0",
                "Nay4E0qsGy8",
                "nUq9X0NKoKo",
                "_Lp5iMI8RWc",
                "K674LKBUukk"
            ]
        },
        {
            "category_id": "10",
            "category_name": "Music",
            "end_date": "12/26/2017, 00:00:00",
            "number_of_videos": 40,
            "start_date": "12/19/2017, 00:00:00",
            "total_views": 101914416,
            "video_ids": [
                "l1hwH4TYvn8",
                "p_IwENcMPOA",
                "ryr75N0nki0",
                "5CG-AXOAYko",
                "l_lblj8Cq0o",
                "0yFXfAGl17M",
                "WS7f5xpGYn8",
                "R3jSBAQ-QoA",
                "sesUrzFWlQ0",
                "_t0LX_Of33U",
                "cMD63TwzB1o",
                "NYSMEzMeMaQ",
                "3TtxYU7oKOI",
                "ox7RsX1Ee34",
                "dmY9PY_IoYY",
                "6CigQPn9jPc",
                "LsT3zZTLEdU",
                "6CigQPn9jPc",
                "5yqNHaolYHM",
                "BevW2gFVYJ4",
                "Jtzn9OQ20Vk",
                "M2q64UowX9g",
                "ORIpWftFyqo",
                "3BXDsVD6O10",
                "ZFy7RdZWwj8",
                "BIQK4-9YFW0",
                "Ku-WC1EaPXI",
                "dHOTgIEmixc",
                "6CigQPn9jPc",
                "tRBsfAIg4-0",
                "jTW5_KvkGoE",
                "CixoPJ-BUGw",
                "hXmBbhGbeo8",
                "RHUxyXZBXY8",
                "eiDiKwbGfIY",
                "3ATQvgkXT9E",
                "X8sSXU-J8fI",
                "xZsONNB3gXU",
                "RQaVzbxZqXY",
                "ItL6vcUrpUs"
            ]
        },
        {
            "category_id": "10",
            "category_name": "Music",
            "end_date": "01/02/2018, 00:00:00",
            "number_of_videos": 23,
            "start_date": "12/26/2017, 00:00:00",
            "total_views": 39702951,
            "video_ids": [
                "_Qu6ReIn46c",
                "ryr75N0nki0",
                "EY-wa1vtD2Q",
                "zbyu6MOzpLE",
                "xWi8nDUjHGA",
                "HPudwr4JwAc",
                "N8s290gKvZw",
                "HPudwr4JwAc",
                "oCnv5wWKDMs",
                "HPudwr4JwAc",
                "PjqKPHZJgF0",
                "XaB0Vfoq7Lw",
                "88EB0TEGQDA",
                "Os9ce4XFS1M",
                "nlf1VClZL-I",
                "u_SA2QkZd24",
                "tRBsfAIg4-0",
                "UumBg2myFrk",
                "mKpPhVVF8So",
                "EdetWtZDTsE",
                "P8mnZpDP38Q",
                "61SWGdZ2p2M",
                "RQaVzbxZqXY"
            ]
        },
        {
            "category_id": "10",
            "category_name": "Music",
            "end_date": "01/09/2018, 00:00:00",
            "number_of_videos": 22,
            "start_date": "01/02/2018, 00:00:00",
            "total_views": 63499071,
            "video_ids": [
                "tynT8gBA6bc",
                "GfCqMv--ncA",
                "smtD5mrdcbs",
                "G4MtkhJehhk",
                "rMQ_TUEwQEs",
                "bVU-MmJZFFA",
                "_088kAE_w4A",
                "CF24Aj0KbEs",
                "Q2EFMOEOdiM",
                "mBrdEYW0Vno",
                "aBL027wEtg8",
                "5CyU5YGx01I",
                "jkkIsJuxoos",
                "gA-NDZb29I4",
                "tBibHSnMJGo",
                "y2-kqsBkYlM",
                "JctVyGslOtw",
                "z2kEKZ6jyQQ",
                "LsoLEjrDogU",
                "x5YbQjvueZw",
                "9sFNGLPtxkA",
                "H4KKMqRDYsI"
            ]
        },
        {
            "category_id": "10",
            "category_name": "Music",
            "end_date": "01/16/2018, 00:00:00",
            "number_of_videos": 18,
            "start_date": "01/09/2018, 00:00:00",
            "total_views": 53144947,
            "video_ids": [
                "biNFtfIVRZ8",
                "8BQqX3bUqtY",
                "ggJMQHltiQc",
                "aKeilu6gBOc",
                "bjDNH7bFP14",
                "b7K_lbglfI4",
                "p4lh1h5hdFI",
                "k3zmNrf0Eog",
                "Mgfe5tIwOj0",
                "dfnCAmr569k",
                "6VUt9T0VAdY",
                "WyWqEFeKX2E",
                "Q-oM2BQ8Jow",
                "2-BnFLtRd1U",
                "DMv7aCwKkrI",
                "k5TqNsr6YuQ",
                "gu9_m0vm7fM",
                "Htu3va7yDMg"
            ]
        },
        {
            "category_id": "10",
            "category_name": "Music",
            "end_date": "01/23/2018, 00:00:00",
            "number_of_videos": 34,
            "start_date": "01/16/2018, 00:00:00",
            "total_views": 80507876,
            "video_ids": [
                "LNHkxOU7zz8",
                "eACohWVwTOc",
                "FovZ7AefAmo",
                "CJzaYLc4pPY",
                "idD1C2-ISlo",
                "02fRdleMSaA",
                "CBjJkO2V9gY",
                "l3vbvF8bQfI",
                "HstnxSr7QX0",
                "QPDitpx-OZU",
                "X6SaVOLRcF4",
                "M4vnmgZLA8s",
                "dTta9D3uCh8",
                "vAh7jTAkCKc",
                "xvYBg6MWPbM",
                "41xo8QEKDd4",
                "pjZuxJ3o_TQ",
                "k8MsKn2QPEg",
                "Mgfe5tIwOj0",
                "sGIm0-dQd8M",
                "NtccSFkAhrM",
                "dfnCAmr569k",
                "7sDgJi9z4Us",
                "kfXdP7nZIiE",
                "x2WrgISUSxo",
                "tNvmHLtqgtg",
                "TnCa71iUVxA",
                "liczsmUSMA4",
                "hTSAyR3nOR0",
                "H83pRUE_kJw",
                "pWT8Snks6oo",
                "mXOTJ-tluUU",
                "S0nbOenwCLw",
                "89lQ5k5F_hM"
            ]
        },
        {
            "category_id": "10",
            "category_name": "Music",
            "end_date": "01/30/2018, 00:00:00",
            "number_of_videos": 30,
            "start_date": "01/23/2018, 00:00:00",
            "total_views": 46084610,
            "video_ids": [
                "No99lbNwBg0",
                "zI8wC1-qDOo",
                "l4XOm1iJuaM",
                "QOZke5DwV_s",
                "lnpne6I5u9M",
                "8MPbR6Cbwi4",
                "Sl_F3Ip8dl8",
                "ZsEiE_eFX7Q",
                "U-am9AabIio",
                "Lj6Y6JCu-l4",
                "pjTj-_55WZ8",
                "3ChgRbqGi-E",
                "wsaq1qsnbG4",
                "-jDBj2UopXY",
                "41xo8QEKDd4",
                "5x-d3pabd5o",
                "ZU9Lc-lvCPc",
                "7AXR5hkPCo0",
                "TWrDnkzHPDM",
                "hYc95vB-nT4",
                "2Yj7dHCAtiQ",
                "RQUuqbzQVsY",
                "9f5zD7ZSNpQ",
                "Q34oY-LI9K4",
                "zkG4Xpz6t68",
                "8ll04Zzw5UM",
                "EA_-S4CGP7c",
                "XblV5A1PlDo",
                "Swoz8Zp4QJQ",
                "_o5zbvGyxW4"
            ]
        },
        {
            "category_id": "24",
            "category_name": "Entertainment",
            "end_date": "02/06/2018, 00:00:00",
            "number_of_videos": 86,
            "start_date": "01/30/2018, 00:00:00",
            "total_views": 38028643,
            "video_ids": [
                "eZ93QZPFRY0",
                "PjK5P7NMyWc",
                "UCSmH6OLPC4",
                "TBBu38sdFpE",
                "fUN9rDzbq-o",
                "LXv6pCFRtYQ",
                "TNKwrOxI1tU",
                "uh9OjpaPIXQ",
                "wtcBquWhjL0",
                "S5GJ4zvNXz8",
                "ykLUJF5B4WU",
                "GC3OKJR7GAI",
                "r7SnpomsUaM",
                "Sl9npEDYeLk",
                "YzmnKcALBqQ",
                "B9rXuK53MNA",
                "ns5GVD8WGdU",
                "byCL99tJ7wg",
                "DTWOHPX9ubQ",
                "DBU2Ufb7k_w",
                "DG5dK269y_c",
                "4DyzIDXLzSA",
                "hnu_vdtBWYA",
                "0I9vWjc9nao",
                "7xEGtnIivoM",
                "HXDxwaS2-KU",
                "gbBhfqM7Mzo",
                "1A_aWbz6D5A",
                "ZOR6EwACgMs",
                "qmxMAdV6s4U",
                "-AtUbdLlPqs",
                "CDi9WO5fLX4",
                "ELGBKi1rf1w",
                "COpBcuZL99g",
                "8jU6rfZF9d8",
                "zi3dvVL-zwA",
                "7Gx74wdaLjM",
                "SGtTgrtONr4",
                "TTvLMb3QmBE",
                "ZREfo8pZCD4",
                "DjbysQgJ64Y",
                "uVPZ-V0EyyM",
                "Hj9XPmLeqOw",
                "YFANYt52m1g",
                "nsxxEsp9AsE",
                "Df4mj8Weu4c",
                "fXMh3VMC9CQ",
                "J6-8DQALGt4",
                "oPnK8_h4LW8",
                "DMT7EnJ_Kp8",
                "pNFfUFwnpQ8",
                "tTMtafubPq0",
                "0BD_oiAvpEk",
                "t8hiBqbueL8",
                "_Oht6ZNXx7I",
                "nGuASCtizdE",
                "gLOxQxMnEz8",
                "C1XiBorCfO0",
                "CeCd5ZWMYjA",
                "BD_bkAycEN4",
                "IjCydO_ZgUM",
                "80T59B2RVOo",
                "7cmzAjwmc5k",
                "ipWfcK1HVdA",
                "_Ig_s9j4MuU",
                "bfLckjKIo-g",
                "8_rTIAOohas",
                "h33u2eeVqXo",
                "bIc6lRYktVo",
                "Cw8rWTmy9dA",
                "ZsvViZgVXL8",
                "UCSmH6OLPC4",
                "IUhe6h6vnE4",
                "aK1_yeAnCNE",
                "nNwiVTtod0Q",
                "jPBERPU7EC8",
                "D-IkMEDaNQY",
                "PzwufgPyTCo",
                "RGzv_s-j1wg",
                "WUdYpaDHmJ0",
                "Za4QbXUZMJ0",
                "Fga6_5AhLl4",
                "4QDDxmtbUsw",
                "vVkxhrSLtcU",
                "1cWD_Nm0tNU",
                "JM2ssSyX7Eg"
            ]
        },
        {
            "category_id": "24",
            "category_name": "Entertainment",
            "end_date": "02/13/2018, 00:00:00",
            "number_of_videos": 89,
            "start_date": "02/06/2018, 00:00:00",
            "total_views": 60532100,
            "video_ids": [
                "A4mzB2PTo-E",
                "01NxGLCVN9w",
                "P3RYvmEmPo4",
                "mmZqOKVvWrY",
                "c43kHHRXkF0",
                "dNW0B0HsvVs",
                "4jEhYOrXd6o",
                "rtiwIkQYUko",
                "3d062S8ILQ8",
                "K3ZwxsTOD_8",
                "h2L6snyHhdI",
                "gvyvh7tmxHY",
                "J9gJqVLT0yg",
                "QdwxKdYG1qI",
                "m3czWsO2Y6k",
                "uKcmhqAuxQw",
                "cYwdp7rRUF8",
                "h-6fIyaVmDM",
                "lfN3wZDaiv4",
                "gpWrT-LdMfs",
                "T1B1CxmAXLk",
                "pVxOVlm_lE8",
                "qq3FniWlrxI",
                "DG6ar_UDwPc",
                "rvPknsWTX6s",
                "vkOt4zmxHhQ",
                "zuC7Oh22ZcM",
                "MEePYLF9Uzs",
                "2Pa9P4jSrxY",
                "J8E1g-cHV5M",
                "M6dc0fnNkfQ",
                "YmCf3a9jYU8",
                "x5O6lhLmUp0",
                "26GaanEOJ1I",
                "Pez3-8fFmqY",
                "doP7xKdGOKs",
                "5QhYCF6Uw6Q",
                "TsxEhxXpLXc",
                "_Jf3yhlpRL8",
                "SGtTgrtONr4",
                "7Wl-OTlqT6Q",
                "j1eKhRDC27w",
                "NWUg_1qV190",
                "YSodwbrmDPo",
                "4vQOD_FiCBM",
                "Ze_qaAOgPls",
                "hthKaOqga98",
                "sBQNCNXMQmk",
                "bYHfxbzhZy4",
                "Pi6zYkbercw",
                "AxMy0D6_DQg",
                "QS8bma7LRX4",
                "2hkhKftPcIY",
                "DaAp7p3ZkIs",
                "gFxuiqQzj0A",
                "bxCZHKL8U4I",
                "S5Q-s-C-q6I",
                "vdqLq6ZiY-w",
                "ZY63ZSUdywY",
                "fPm1nqe6EYc",
                "67zapJrmyWI",
                "dzxFdtWmjto",
                "8qmYHYW5GR8",
                "ZlPgrJFMFYY",
                "EU8iF-8zE-Q",
                "WskfvEBmW6I",
                "hSvnepZS26s",
                "hiqEFs2okMA",
                "T4e8_FClVSA",
                "7cqYiUmutGI",
                "9sIltKnbmwI",
                "B7meAh0Rm1M",
                "Q0ITVHiQYEw",
                "NooW_RbfdWI",
                "5hQ1muZG62o",
                "81f6jCUJF0E",
                "5O6iNs0cEIU",
                "8YIy7NFdMQw",
                "-9gMPpMRODE",
                "6yEewqyHnqo",
                "ogmIGZOi3e0",
                "A1poQzpOf94",
                "9Dmcbd293K0",
                "9c2kibBIqKI",
                "V0twCKDP3C8",
                "RS_0sVza0nY",
                "Pf5JMwXOy28",
                "5nItNLfdwe4",
                "-t9TwUaJUUQ"
            ]
        },
        {
            "category_id": "10",
            "category_name": "Music",
            "end_date": "02/20/2018, 00:00:00",
            "number_of_videos": 38,
            "start_date": "02/13/2018, 00:00:00",
            "total_views": 94691593,
            "video_ids": [
                "wfWIs2gFTAM",
                "-9C1Z3nIsPQ",
                "_hMQe2U4c6w",
                "jzD_yyEcp0M",
                "PLKy28vFfL0",
                "aVOh7jFjFpQ",
                "D4fC4HVpP3M",
                "wbxSWHzPDIc",
                "8iEcQPRRh80",
                "91dCMceBGkg",
                "lzLQP25bTBk",
                "1i4krQH-2eg",
                "PLKy28vFfL0",
                "uYmpUa38-Fk",
                "xYtsL9znopI",
                "QQ_3S-IQm38",
                "UlXPdOuNU3Q",
                "izIyhdEHSPo",
                "fpAopipfdAs",
                "kLpH1nSLJSs",
                "gjL8WNQluTQ",
                "HU5vtxfspjs",
                "n92qIk6nU84",
                "9S1Gc1nSXd4",
                "NV-3s2wwC8c",
                "wIimU5-UEPc",
                "jDnWeqmEiqc",
                "WVVUjOulUj8",
                "GYLBjScgb7o",
                "XRI07X_6Q-A",
                "XUqRem0W8L8",
                "dbn2OvD8DdQ",
                "7IXQREfdy88",
                "zgEo2dhgAOo",
                "7R1N-8SoqcM",
                "mvppwULNJLo",
                "VwAnsAUYnw4",
                "pC2yUlN2kMU"
            ]
        },
        {
            "category_id": "10",
            "category_name": "Music",
            "end_date": "02/27/2018, 00:00:00",
            "number_of_videos": 26,
            "start_date": "02/20/2018, 00:00:00",
            "total_views": 63093573,
            "video_ids": [
                "xpVfcZ0ZcFM",
                "RQpPhYSUrsQ",
                "tGRzz0oqgUE",
                "9XaS93WMRQQ",
                "EAGhzuitLXU",
                "0h-kHHurkBQ",
                "WlDVOIO1rIA",
                "MGYJuETPQEg",
                "hF6Wds75rjg",
                "AubUZV8tWKk",
                "hFMzzV-viVE",
                "UCoogBnurWk",
                "tHtnxluMXMw",
                "lKL-5el7rb4",
                "4EVFKrmXFmA",
                "dhVK4jbjMSQ",
                "-C_rvt0SwLE",
                "elwTgpHlty0",
                "s71RmkU8OuY",
                "k1xvol1SCx8",
                "6-lostV6sk8",
                "gpw8RIb6IFM",
                "HBfEf9MsRr4",
                "82sSofpc1II",
                "Sm2ArOlORFQ",
                "CngjMRWYNHs"
            ]
        },
        {
            "category_id": "10",
            "category_name": "Music",
            "end_date": "03/06/2018, 00:00:00",
            "number_of_videos": 35,
            "start_date": "02/27/2018, 00:00:00",
            "total_views": 96992952,
            "video_ids": [
                "OK3GJ0WIQ8s",
                "E-u9uo0laA8",
                "-sqBQ2cE_uI",
                "T3hXC5yNZOc",
                "WNRZGOx5aaw",
                "pgN-vvVVxMA",
                "SFKPktgfQdI",
                "XR7Ev14vUh8",
                "MGYJuETPQEg",
                "bmf1wPXkMNA",
                "HgknAaKNaMM",
                "BQ31l1gPGKM",
                "WBU89etq2NI",
                "xuAH21DkJow",
                "i8J0cR-PY9c",
                "kton-qrKNLc",
                "LPTlvQ1Zet0",
                "SOjwzWWR4lA",
                "_I_D_8Z4sJE",
                "_qQsPw4CqUI",
                "OHap45tpS38",
                "E-npMl4Sb8c",
                "8GGGliIxpgc",
                "wRQEfN8PGYI",
                "QdnvoWyoiY0",
                "ON6fCdE0XiM",
                "c77skI2QgrA",
                "DGhPGH2YROA",
                "KAS8zQt6Wik",
                "eCaBAzi6yjk",
                "2fQORuHsuL0",
                "yFFL1we4j_Y",
                "i_nLsG_asQg",
                "YPZUkzgW_DQ",
                "xaqwV7jisic"
            ]
        },
        {
            "category_id": "10",
            "category_name": "Music",
            "end_date": "03/13/2018, 00:00:00",
            "number_of_videos": 26,
            "start_date": "03/06/2018, 00:00:00",
            "total_views": 64354337,
            "video_ids": [
                "Ph54wQG8ynk",
                "fuoCUfdqZFI",
                "lhnmVSB-Rxc",
                "Udd6cR9va4s",
                "Rter-Np-Td0",
                "li95v2oLcLw",
                "oMKYLxwhAo8",
                "Qvd43XKY-f0",
                "-BQJo3vK8O8",
                "13_mawXVXnY",
                "KCnKJbNSibA",
                "ogyVcszhaKM",
                "-x22MszTTC4",
                "8iFGgfJiLsg",
                "8XiqrERZo_8",
                "ToY6sjSV8h8",
                "LJjsm6CVsG8",
                "gRYcx0u9y-Y",
                "36uAfi8yLGs",
                "ILm-b0Gw7-E",
                "fC8gutkCu1c",
                "12dANV0FHgc",
                "oRArmtMA9AI",
                "_AsPY1bQx70",
                "YLOOdfifC3Q",
                "b2RHgyH-Nxo"
            ]
        },
        {
            "category_id": "10",
            "category_name": "Music",
            "end_date": "03/20/2018, 00:00:00",
            "number_of_videos": 24,
            "start_date": "03/13/2018, 00:00:00",
            "total_views": 55216844,
            "video_ids": [
                "S_s_Oz7ropA",
                "gWmz4U65kls",
                "sS0LCjOiIhc",
                "DMl1YJyqEdo",
                "1SnWTW6YXbE",
                "-59U4Bgn8V0",
                "mlf4bidp2yc",
                "gj7ngd5iy0M",
                "nqzIQh2D_Es",
                "S1fG1WjTAQw",
                "Thvm6dADOms",
                "tFCoxg_XxHc",
                "fzCct3j-pH8",
                "tCXGJQYZ9JA",
                "XvIpLfV5GKo",
                "pZ301QEoo9Y",
                "95Rzsn-zjr0",
                "wjdXv3bOtqc",
                "sPK8bwoqJvI",
                "Txlk7PiHaGk",
                "8OARiNiJ_w8",
                "1YQDddDKz_I",
                "3Kt5tobRNt0",
                "ww2lWzwbnIg"
            ]
        },
        {
            "category_id": "24",
            "category_name": "Entertainment",
            "end_date": "03/27/2018, 00:00:00",
            "number_of_videos": 94,
            "start_date": "03/20/2018, 00:00:00",
            "total_views": 50007381,
            "video_ids": [
                "8C3FN1A7PrQ",
                "HXxIXoh3M5o",
                "1BMhKFNoG94",
                "of2jhOQjT-w",
                "nsjPEcRq_0c",
                "MiUFhVrG598",
                "JhvwFB-NUbA",
                "QwievZ1Tx-8",
                "SR9sjchWadI",
                "6ojjvi5gUaU",
                "Hw7BWXPa5xM",
                "9WFf9XY5rME",
                "ioa7vFjTJio",
                "4_pgz5iKlsA",
                "zcQm-utrusw",
                "xnNTUN41BLQ",
                "5mar5AHglGI",
                "Gg9dYwd-Nfk",
                "SIgOf_kVDj8",
                "4_0Q2OX9Mic",
                "H0rcx9kAAZs",
                "BO9opiX7_5M",
                "hp-zb4cj1Lk",
                "FhwktRDG_aQ",
                "jYTy1SMx-DQ",
                "gjQ1Brofle8",
                "HoimIkxSCSA",
                "YFGg82Gq96o",
                "_H6Yf8Fm6R8",
                "LNjiBBCNkk0",
                "i3LYAnP6qlU",
                "OPdmg58S9ZM",
                "Ku52zNnft8k",
                "ZCPwpcurYns",
                "mhog9LEMCDY",
                "FwENtwtY0EI",
                "_8c_eg8V9S4",
                "j8ZP0j64g_w",
                "pVdZIygLH10",
                "raymwkMf04g",
                "sOl2aj5nuck",
                "VwWV4JelEzY",
                "zsXvDRuNCF4",
                "m--0_3vTr8I",
                "2pL7aDAoteI",
                "Dpk_EbOlOFU",
                "kjC1zmZo30U",
                "5TxN-3GfhcA",
                "apyD0QGObZQ",
                "z1Fvrmf4BXc",
                "zZcqgKUKD1w",
                "l_IFnDydIeQ",
                "54BVvP7zvDQ",
                "xPL6fpkZ8aw",
                "XKFKPQHdWRI",
                "fJZht2-Kg3w",
                "yH2Bu7Zxjg4",
                "4csQhMHvQWk",
                "DfxhWPvhFCQ",
                "rxKOcte2JSs",
                "dRfvXL-m7O8",
                "5r-07Lsb2Mo",
                "ikH62qCV5Bo",
                "WJ6F9NG2UWo",
                "hubcUCV5J-I",
                "DkiyT-dnmv8",
                "VvWB-Yhhm8o",
                "jzIE_oKG9PU",
                "Vv8pcs0C8bw",
                "pMMb3DUM9Q8",
                "HFavQ6TNFtA",
                "43hsIO_Jxtg",
                "Ivl044_cFS0",
                "l5Pq26lOMWM",
                "fH5SelF_glc",
                "xCwwxNbtK6Y",
                "KC-mhZz7n6o",
                "vdlaCs1RVHA",
                "EgNxiVub-Ds",
                "08P1En_h2tg",
                "HQ05mj3s1Ls",
                "_MeQz8OWXQ0",
                "ZSnVjIUqwSg",
                "1i0lt1njpUw",
                "pF1h93bdwjs",
                "SoB0fmO0Tiw",
                "QwUq8xM_8bY",
                "fjMw5Le_5jw",
                "3Qez7PL-FOo",
                "9OmSGgZlIK8",
                "zSodCKWDGx8",
                "mOyB0njcxqI",
                "926hMiVuP9Q",
                "Mp4LeOWNzXI"
            ]
        },
        {
            "category_id": "24",
            "category_name": "Entertainment",
            "end_date": "04/03/2018, 00:00:00",
            "number_of_videos": 87,
            "start_date": "03/27/2018, 00:00:00",
            "total_views": 48935874,
            "video_ids": [
                "P62zQv5JNCI",
                "d-_s46Uob5E",
                "wTeTHjpPMgU",
                "TtCrs2JSUEg",
                "dc89yyOS0Z8",
                "WEMAvnkHA9U",
                "kzqig4utv5g",
                "qrks9Zu0f1w",
                "-aI1eQwVewI",
                "BHh3LG6vWxY",
                "Z7tkcyXkLDY",
                "w68kHdbUp_0",
                "w6Z1L_HHCcw",
                "JrmxD9UxY0E",
                "wdPSw2uQj6M",
                "sudG0ziGP7U",
                "1icvATK0GEo",
                "3lgcBZdMZxM",
                "Ml9v3wHLuWI",
                "gQZChW3JKV0",
                "StjYXOSMJxk",
                "ylxzfecackM",
                "CD4MptwCvWM",
                "c2fJ2qeSxhk",
                "NxgQH9M6hg0",
                "FNdyDazu3V4",
                "WzENmD6XtNw",
                "UroDMfQv5L0",
                "Ovu9a6ntSPc",
                "fmOP68S5v7c",
                "TkWmK-cplV4",
                "m786k0quYdE",
                "NlkfPR8PZSY",
                "8A7bNJCjkx8",
                "eqvXUOwArdI",
                "ecrM2MqNlAM",
                "j8giXiRyGbg",
                "bij6z62f5t0",
                "q9NpdN7r3O4",
                "i4ZkQPHlWZM",
                "wtgsk8hKac8",
                "R_O5x0LNksM",
                "fgnhU_qA4RQ",
                "nOphT8zxFhA",
                "uTRUQ-RKfUs",
                "qnQuwPQ9uTQ",
                "m4KK_UqzFAo",
                "H5UxLyOT2zI",
                "Yiql8roK3Hc",
                "CeCgsmTjHjk",
                "iSZq3l-Fmbo",
                "kxkrdLI6e6M",
                "J8gUz1FkAnY",
                "KxP4LuS26ds",
                "4t6sEGeFoqo",
                "OVRjkAjE8j0",
                "E4691igUPG8",
                "MVEyFtc2f-Y",
                "0WEzJX9Netk",
                "HfoHeCBshCo",
                "eHQudvHID7c",
                "wo7ItkoCYok",
                "OWvrFhCFR-U",
                "t-My3vpDBvA",
                "nbFoHzqmZ8o",
                "3BNg4fDJC8A",
                "Mzh4AARBavU",
                "dKoIPuifJvE",
                "z-JurmXtLCY",
                "RLLOqUGfTCA",
                "Cx66RkjggLk",
                "LBeOQlKpM8Y",
                "RF-Mqs2qC-M",
                "qguc70jfWmo",
                "jghZXw5RNGY",
                "oCPLcZ_tneI",
                "SxaMrCpigNI",
                "ohn3zb2BZzg",
                "qyeAZiEo5Bw",
                "iR3m-HWROu8",
                "Iqbhl20fyaY",
                "-6b65coGHRY",
                "hibFNdLYBms",
                "8NXGdl9EBgM",
                "HYPkP8eCU6c",
                "VVMCz04CmlA",
                "yDuqRqQEDsA"
            ]
        },
        {
            "category_id": "24",
            "category_name": "Entertainment",
            "end_date": "04/10/2018, 00:00:00",
            "number_of_videos": 43,
            "start_date": "04/03/2018, 00:00:00",
            "total_views": 19852273,
            "video_ids": [
                "H_HBY7h8K1Y",
                "sde3ke1Qof8",
                "LF3v1GI6APU",
                "5aISC84gXBw",
                "4UO9E3Tb1Qc",
                "vb97DrNDSfM",
                "FH7wH9doJ9Q",
                "xXf2ct7C2fQ",
                "SsyUGltfuZo",
                "3-1LFKZr188",
                "p1bV1gZ1cvU",
                "5Z2p6Vo3S-E",
                "ACHZrvF6mTA",
                "nQ1mmVG-G1g",
                "B-J_QhzLfHw",
                "dn_aaxZIA2o",
                "muZIRQZLDWk",
                "ZUs4JxQJAv0",
                "ipjNJS6-TyI",
                "hnKvVZhZ2sg",
                "j8gXtP-oqmE",
                "S8e1yxXiODQ",
                "42FRgdjveGU",
                "-Qv6p6pTz5I",
                "t9QtXGirWf0",
                "-wuvYC0x5lc",
                "FBIkUV4I1aU",
                "rQG5W2HFV3g",
                "k2GIo7woPiI",
                "14wNmoAqPyc",
                "AcqCSonRQwk",
                "aEvItEpMly8",
                "omczdd9JoQo",
                "2AQw7OrDAMw",
                "IoZ5qDUuPV4",
                "SCjVcdHHb84",
                "guRbfQFddfg",
                "vGBrCXIMkQA",
                "0XJQ0o36wkA",
                "LJuYzh3UDGo",
                "bvNonoGTjgw",
                "ElPJr_tKkO4",
                "1dp-q0Zevxc"
            ]
        },
        {
            "category_id": "10",
            "category_name": "Music",
            "end_date": "04/17/2018, 00:00:00",
            "number_of_videos": 23,
            "start_date": "04/10/2018, 00:00:00",
            "total_views": 45384025,
            "video_ids": [
                "oCXvPWJClJg",
                "_NWs7ntMRBA",
                "DPxL7dO5XPc",
                "hOiHshb3BKs",
                "jPMJtUpiTIQ",
                "BidS_rcf7UU",
                "3TCcDE4fi4Y",
                "SCq8n_hOcN8",
                "dUaCEs3HfdI",
                "OMJCsytmfnw",
                "jDHI8oQ_Zu4",
                "PaYvlVR_BEc",
                "E8jrQAmQYRA",
                "R1TSiB9OuVM",
                "vA6z9KaWXjY",
                "J-dv_DcDD_A",
                "rzgw0XldTC0",
                "C_ijc7A5oAc",
                "M4ZoCHID9GI",
                "HHyPo8VR8I0",
                "p6E9R9qv1No",
                "9zUHi8ON6PI",
                "67LFrXVIA00"
            ]
        },
        {
            "category_id": "10",
            "category_name": "Music",
            "end_date": "04/24/2018, 00:00:00",
            "number_of_videos": 39,
            "start_date": "04/17/2018, 00:00:00",
            "total_views": 91232882,
            "video_ids": [
                "3QMKdZ1D_4U",
                "1gXx_WVk_SE",
                "NYMcACJLqJs",
                "45GaTIIdL7A",
                "qSIY6C1uv4E",
                "g4HDfqEWf6Y",
                "yO9snUMvRuU",
                "rsWmrGuuWuE",
                "EHUYNVA6hF4",
                "M38aWHxwtXE",
                "zEf423kYfqk",
                "DX5_o-mumvE",
                "wLBrjrcMlCo",
                "vvEUSUVk2kI",
                "DPxL7dO5XPc",
                "Z4b6BPaO944",
                "z5WrgDzNIZ0",
                "tlILlcCE8Sc",
                "fNVUTgd4pio",
                "4fpAt_vnbF4",
                "aDBMVKtcG2Q",
                "UCdMwyIy3ks",
                "ffxKSjUwKdU",
                "h3cgHyusc5s",
                "whwUlzuLfs4",
                "KYxIC5wQw0I",
                "2ha8YQ0SyyE",
                "cpGA0azFdCs",
                "XWtJDG-Cdgw",
                "uutnsezrTEQ",
                "vUTI4bPdlgE",
                "TdyllLZeviY",
                "lPiIp5QuTRU",
                "MctZLEYlU4s",
                "ayb1wJ9_Xmw",
                "hjf-h6NMj7U",
                "LFSacMbImys",
                "f5I79eakR8E",
                "ISPadKRsrqE"
            ]
        },
        {
            "category_id": "24",
            "category_name": "Entertainment",
            "end_date": "05/01/2018, 00:00:00",
            "number_of_videos": 80,
            "start_date": "04/24/2018, 00:00:00",
            "total_views": 92431986,
            "video_ids": [
                "dyoGXhIj1UA",
                "KiuV9VxYa2c",
                "BG7EdPwkUxQ",
                "MlhajJrQZYQ",
                "skxMIyrdfzc",
                "k2ncBw-Y-Yw",
                "RoflWNvJg_w",
                "sGF81Z1Kols",
                "cyIftAPf7kM",
                "CagwvHRMPGE",
                "gxepM2uSW9g",
                "rdL5Diq49CM",
                "l3pMdIb0XJ4",
                "0SStOLbYK7U",
                "tHmAPWOo2jY",
                "UnlXTNZ2e7U",
                "v3fvyCzRqfg",
                "FRQL_CXrqzw",
                "VPrZ12oweLI",
                "eKR_n4alu3o",
                "Eh5eWMn9mJM",
                "baG767jr8c8",
                "VRCwJocpk6Y",
                "94k6kEVGZzg",
                "HBtwa1q_NNA",
                "rRr1qiJRsXk",
                "xNm1rfMzyVw",
                "WttN1Z0XF4k",
                "EaDrjjXBB60",
                "v-hzyV5cpes",
                "jQ9FKv7TA_c",
                "bSJ8mpWBVeE",
                "UypNWebswzI",
                "YDQXzY11aS0",
                "T8phn9cGgV0",
                "qTMU2nQ4wGg",
                "C7lQ_jqSqKQ",
                "jR-Fr-cXhkU",
                "bZs2ImrTg5w",
                "f_0duM9EQx8",
                "WRQSERxTvYk",
                "8qitxIJAdLU",
                "eIp7PYuAu0k",
                "9fB0GBwJ2QA",
                "_1I7k_uMb4c",
                "xsqInns6LXQ",
                "C7lQ_jqSqKQ",
                "tK8YsKLQXIo",
                "FeCjf_ZxxQc",
                "IZODr96ZRCc",
                "R1s0VEk9vgw",
                "b5Vmaw4I55s",
                "Kl0UEUsyPf4",
                "i0L6IlttNKQ",
                "ZQ-YX-5bAs0",
                "vIxs3A0y47c",
                "RFHGVQ6Ni_I",
                "WS8ilm5YO9Y",
                "0hdnQ8EXdEs",
                "rfx3eaJWIvc",
                "d4kDR5dresE",
                "bFIB05LGtMs",
                "KxOmVH3npF4",
                "ZNkYsvrVSnQ",
                "OO8bo_fpoQg",
                "5JYqTSSH6IA",
                "t9MzWftt0ls",
                "kdDyAw0ihq0",
                "p8t4HQWwDxk",
                "OfDpFTNnRyg",
                "35twNGPBtgk",
                "gGnBX6e3RJc",
                "yc-iu4MjK1g",
                "s12qaVEyW14",
                "h39fZdU7174",
                "OXztwkG66PQ",
                "kXOIJ_pXqRg",
                "u9Mv98Gr5pY",
                "OXztwkG66PQ",
                "YKWGQyz-oLw"
            ]
        },
        {
            "category_id": "10",
            "category_name": "Music",
            "end_date": "05/08/2018, 00:00:00",
            "number_of_videos": 35,
            "start_date": "05/01/2018, 00:00:00",
            "total_views": 103374840,
            "video_ids": [
                "qSKOPBVkpJk",
                "Ab7wBY666vY",
                "xzHJ2aZR6e4",
                "1E9j4689ZWQ",
                "ucVJrja8r6Q",
                "maDPbJaiJy4",
                "Wpm07-BGJnE",
                "G7RW-KVDeEo",
                "oMNqsSVuYvA",
                "YWyqZ10qBR4",
                "VYOjWnS4cMY",
                "rItv9i6c7AY",
                "HhoATZ1Imtw",
                "5GHXEGz3PJg",
                "vjI4Alon-3Q",
                "B7mNS5ygvAQ",
                "tsp7IOr7Q9A",
                "5orrZxSjLQA",
                "Bs-Hr-gEJAU",
                "CX11yw6YL1w",
                "dARAN1z2KqY",
                "tcaw6lzYt1Q",
                "DuPFBprNjcQ",
                "cyPyIj08drw",
                "o27M0gXjUqk",
                "0_Ay0zBns1w",
                "P3iLo_JI9oY",
                "d-xSH9zlKpE",
                "35GMuSbNav0",
                "DkeiKbqa02g",
                "XJT7I0sLdD0",
                "RWFdAgFRDfI",
                "DSRSgMp5X1w",
                "bFCVXPTJt_4",
                "rxmtHVSVjdo"
            ]
        },
        {
            "category_id": "10",
            "category_name": "Music",
            "end_date": "05/15/2018, 00:00:00",
            "number_of_videos": 32,
            "start_date": "05/08/2018, 00:00:00",
            "total_views": 103148870,
            "video_ids": [
                "XIWcAnybqB4",
                "b5FcAHC0JSo",
                "YpU0y6TMGSU",
                "HbaQ9xnoMGQ",
                "VYOjWnS4cMY",
                "32sYGCOYJUM",
                "tjA7nAHOAww",
                "RqjsstB1uKA",
                "iILJvqrAQ_w",
                "t0mXOsUkY8w",
                "YXC2C6o9EgI",
                "2PH7dK6SLC8",
                "eP33TkuI9vI",
                "eOVOp0uO9cY",
                "sPPmWfHhyBc",
                "-3b2Fov6iQY",
                "nrVNAq7nSTQ",
                "lThYfJvudTk",
                "Dto7Nms-Xo0",
                "l884wKofd54",
                "VQhjbCxOxdo",
                "8h--kFui1JA",
                "FkOt19CUC30",
                "AebsJPV2ZYM",
                "ybp7SDwlzME",
                "fF7ndg3_4AI",
                "py2Z-UNKtes",
                "7sZ1t8_47RY",
                "3SUGgvfyqDQ",
                "xwCPIaVA0sQ",
                "Ab5aV-wekP0",
                "zzO3J_pp9vc"
            ]
        },
        {
            "category_id": "24",
            "category_name": "Entertainment",
            "end_date": "05/22/2018, 00:00:00",
            "number_of_videos": 103,
            "start_date": "05/15/2018, 00:00:00",
            "total_views": 80433721,
            "video_ids": [
                "9du6mAxEBtk",
                "JIJB7cv97Dg",
                "ET2iZV2GqJg",
                "HTTpDGDAxtg",
                "86DCTSyzXsw",
                "WqB0CE9YjCs",
                "3Gysq0XV-IA",
                "o8oYmaasdA4",
                "P4t80OyKius",
                "UfKmSfgFxi8",
                "AuQkjFfVho4",
                "f_R9_xdhuNw",
                "v7UjGdubx6k",
                "Gb1Am-33gTk",
                "t4pRQ0jn23Q",
                "MWb2vazaD28",
                "a9DiyVhniYE",
                "nwluATd-HQc",
                "YkmD7NSQcjM",
                "t4U7nMn6nfs",
                "Wbm-GzCnC-g",
                "XvpGvVR1D0w",
                "1L8mTXxK-fc",
                "_QWZvU7VCn8",
                "wswvNZveNHc",
                "M0Tth-0MNFk",
                "C6SCvFee8tQ",
                "evKZGQ-qwEE",
                "qUSmCQ4gUjo",
                "UDlpZJ8EG8c",
                "nCnUim_gjsQ",
                "vJ5DaMdqlIM",
                "eiudTjsGM7g",
                "Gjc0gXDE3aU",
                "feuetv-nU7M",
                "20d1g6O6Fog",
                "5gy7wSLhJr8",
                "h2lfKH-FBds",
                "nlozE2m-NMc",
                "M5RsnRRvDs0",
                "AWU3_jyEStk",
                "S6rDvbQ-mz4",
                "ubyAEacslEI",
                "9m50v0718Vs",
                "fotYFcF-x_E",
                "CQQit01HHLY",
                "HrQNdClwMs4",
                "Yjr-A_nnDdI",
                "_IiCh41jLnU",
                "QNZ53Cpl9B4",
                "atLL2Yzi3bg",
                "ffbyaX9Ymt8",
                "gtGbF7JqxTY",
                "ycS6LjhZHdE",
                "-PO2jJjNzsI",
                "9Y7X6le5qmE",
                "KObL442PWhQ",
                "YdOcH42JI48",
                "z5ny5inHBac",
                "xhs8tf1v__w",
                "AyqCoftMjvM",
                "jua2rmJg7hI",
                "SLL6gpy00WE",
                "_MOVYyJqIdE",
                "UNPqnEtuuiU",
                "bVeAdzNU2ow",
                "8_Okz_CN34Y",
                "rfUTVQjUZls",
                "pFc6I0rgmgY",
                "xBht9TG7ySw",
                "F6SIFCgipC4",
                "CTH_cEmp6Kw",
                "4o0cU2-IlCE",
                "YCYSWUeA8W8",
                "emuMxrTL8YQ",
                "7m9dAbmtchQ",
                "i8EJkbADR3o",
                "hiBPUpCJ7MQ",
                "QYU8w4ONQVo",
                "ZxYt2s8FZi8",
                "OgiY3OR3jlg",
                "8U-17XtqMWw",
                "QxTtsZUcOjQ",
                "hExxZdkSfuE",
                "048WlirXNXI",
                "BO7yUdPHeo4",
                "5fDeKPgVHVo",
                "AuSVnJJOsuo",
                "o8KtKp9v750",
                "2LF_WLiyM54",
                "uqLy3XHIg4c",
                "XF4_DvnNeCQ",
                "pE1Qk90pxE4",
                "X-eRc9PF3TU",
                "R3gYYWIAaM4",
                "Txsj-DgYbv4",
                "PzxnMOGQWCk",
                "QW8whgmyTNU",
                "2Sk3C2Glo88",
                "pwj_SZHqiSc",
                "4_aR3HqFrr0",
                "ciiwjn8jyvU",
                "HX3tKAcCcxA"
            ]
        },
        {
            "category_id": "10",
            "category_name": "Music",
            "end_date": "05/29/2018, 00:00:00",
            "number_of_videos": 34,
            "start_date": "05/22/2018, 00:00:00",
            "total_views": 57468683,
            "video_ids": [
                "scLYjsvrUMk",
                "Yo0RvZZz_ds",
                "Fj3euSYAtnc",
                "8dfXKIzU_24",
                "bFoJFJ8ZrdM",
                "UW_xEqCWrm0",
                "8zSRkr1nQNw",
                "aEM2kOrrNJI",
                "70qndlGsQAs",
                "Qr_QLv1TPcY",
                "RNlQU-7y9Fo",
                "E5bO-chVuZQ",
                "Ytzc6ehAvOM",
                "lN9WqViMBKk",
                "WMIDCVupz1M",
                "au8QGTiPhEw",
                "D9kxpUcWID0",
                "UKserM-i0_A",
                "QgOXIEhHU1Y",
                "o-uWRhi2ngE",
                "oLDbO545aKQ",
                "tuBMDapQr3A",
                "qeZw0c56bgQ",
                "SWAXUbqda_E",
                "mQ055hHdxbE",
                "f1FX5wvC3DA",
                "giOZ3EAleeI",
                "5Y-5vrFEmdY",
                "voG07pt-KYI",
                "NxqjMiFe-rQ",
                "G3Sl2vJrmf0",
                "3Q2j5ApzSqs",
                "LBouZZqO0mc",
                "kFMZUxX6K6o"
            ]
        },
        {
            "category_id": "10",
            "category_name": "Music",
            "end_date": "06/05/2018, 00:00:00",
            "number_of_videos": 37,
            "start_date": "05/29/2018, 00:00:00",
            "total_views": 123173295,
            "video_ids": [
                "uSVW0aJdn9o",
                "8OHLAZwegM0",
                "zUzBfBqbSmc",
                "HZoX-10-VMs",
                "aJOTlE1K90k",
                "d8O6SoPOkAk",
                "6Wi2d8ziX9M",
                "TuTDc9d_9yI",
                "swqmsRWM4rY",
                "2SJ0hgdciNE",
                "FnaqC2ZH3Z0",
                "MN840bAdQyw",
                "sfU0qBEbY_A",
                "doAq2FutWYA",
                "xTlNMmZKwpA",
                "8JnfIa84TnU",
                "JrO46CJd9ns",
                "uZwsYdxecA8",
                "_FyNKmnsiuM",
                "joiZ3SZdC2w",
                "xirk18P889U",
                "YynKelHGhNc",
                "QHo7c8x7wb0",
                "nHjHfCeBkmc",
                "wS4ESheuHDY",
                "VmwOMtkDxtk",
                "IIPGgPCXvgU",
                "E5yFcdPAGv0",
                "UxDxZH_YaO4",
                "TS71fTCL8zw",
                "ntWSnDV0MYs",
                "f_akFYKDA64",
                "66Zw9sKfjOE",
                "z14A0Vblm0I",
                "e6akG3Wsd5U",
                "E4c7EE8_IX0",
                "D_6QmL6rExk"
            ]
        },
        {
            "category_id": "24",
            "category_name": "Entertainment",
            "end_date": "06/12/2018, 00:00:00",
            "number_of_videos": 86,
            "start_date": "06/05/2018, 00:00:00",
            "total_views": 81218876,
            "video_ids": [
                "ExJmET8boVw",
                "0Np4K_PAfnI",
                "3A8iPnSkM2A",
                "zUcA9Xzm_oY",
                "jYv3rsW3NA4",
                "8u-u29n39_Q",
                "g4Hbz2jLxvQ",
                "v2dem7H9ick",
                "1GhIVG_Sh3Q",
                "qA6vrnwz_AI",
                "lweS0jok-Pg",
                "bF_naHpa-T4",
                "NN4PegHL8dc",
                "DxGlBTPEx5E",
                "5O0N3u9-m7c",
                "G36BAjlL3pw",
                "wloLgnGZxJk",
                "JfsxLhPn-oA",
                "XwYIhu0vXYY",
                "jBBnNLDtP00",
                "qFy5XyZsUeo",
                "vIohS0xEIe8",
                "4iRJDDjejCI",
                "TEsebOvBInQ",
                "GC321SaaOck",
                "bdcn9JtiPOE",
                "GnGPAYvve1A",
                "X2GJWR3uN_U",
                "nV-Ox4tPcwA",
                "vChxaZCecLw",
                "afAI_FvUcsY",
                "GgBOK8r5foQ",
                "68qhGBZzYYk",
                "6joxqWBE5lQ",
                "2s4GMLkTNv0",
                "HX1RBvIGsj8",
                "Z0ekMVs1V1E",
                "0TNVthqZ3uc",
                "hRF9Y6AfGx0",
                "q6c5DRGjgHw",
                "xPZc0dC3wVY",
                "HeNLNc_29zY",
                "njIP93V9qYg",
                "AMqSY_zBP74",
                "pN4aJUFuuug",
                "cXf5SOhwu1A",
                "rKVNWQz1qjI",
                "R2NRbhc3T5M",
                "EMq-R4RF928",
                "SvyBemoZV1A",
                "4SZqTeF5PYg",
                "KRc50VFUsTk",
                "ek0FPAt3ydQ",
                "6KAEfOcdBd4",
                "5I8Q5AVxWaM",
                "JYDGEMEXyqM",
                "Y3KKQh6BrQQ",
                "T2YJYVYYhfI",
                "_THBex8DItY",
                "0WjNXuqmbJ4",
                "54vSt1L8nvw",
                "K-YCsUa1mZU",
                "MsQb18nU2hA",
                "hNcWlRQWMc0",
                "1yAJ4MH8mss",
                "ek1ePFp-nBI",
                "-ceGIszLBoc",
                "vTwOhPPQRW8",
                "-GPUM7RQ76s",
                "RDybuhERj_s",
                "VPSoNx1gyQ4",
                "u2nEjXJtRJ4",
                "xQkOp1rcCDg",
                "S3bczp0NAs8",
                "hj0dL7wwT2U",
                "8cFzdxwha48",
                "4QZ5xwccPa0",
                "KHQhp2cGZtE",
                "44fjX-rgJ7s",
                "naW9U8MiUY0",
                "Scvw6Q-pPeE",
                "Jodbdj52Vc0",
                "QwNf7mWQmFM",
                "SiduJA4p7SQ",
                "XvHSlHhh1gk",
                "ZsKXq8AQTZE"
            ]
        }
    ]
}